[
    {
        "book": "1984",
        "author": "George Orwell",
        "publishing_year": "1949"
    },
    {
        "book": "To Kill a Mockingbird",
        "author": "Harper Lee",
        "publishing_year": "1960"
    },
    {
        "book": "The Great Gatsby",
        "author": "F. Scott Fitzgerald",
        "publishing_year": "1925"
    },
    {
        "book": "One Hundred Years of Solitude",
        "author": "Gabriel García Márquez",
        "publishing_year": "1967"
    },
    {
        "book": "The Catcher in the Rye",
        "author": "J.D. Salinger",
        "publishing_year": "1951"
    },
    {
        "book": "Pride and Prejudice",
        "author": "Jane Austen",
        "publishing_year": "1813"
    },
    {
        "book": "The Lord of the Rings",
        "author": "J.R.R. Tolkien",
        "publishing_year": "1954"
    },
    {
        "book": "Brave New World",
        "author": "Aldous Huxley",
        "publishing_year": "1932"
    },
    {
        "book": "The Chronicles of Narnia",
        "author": "C.S. Lewis",
        "publishing_year": "1950"
    },
    {
        "book": "Don Quixote",
        "author": "Miguel de Cervantes",
        "publishing_year": "1605"
    },
    {
        "book": "The Hobbit",
        "author": "J.R.R. Tolkien",
        "publishing_year": "1937"
    },
    {
        "book": "Fahrenheit 451",
        "author": "Ray Bradbury",
        "publishing_year": "1953"
    },
    {
        "book": "The Odyssey",
        "author": "Homer",
        "publishing_year": "800 BCE"
    },
    {
        "book": "Crime and Punishment",
        "author": "Fyodor Dostoevsky",
        "publishing_year": "1866"
    },
    {
        "book": "The Divine Comedy",
        "author": "Dante Alighieri",
        "publishing_year": "1320"
    },
    {
        "book": "Moby Dick",
        "author": "Herman Melville",
        "publishing_year": "1851"
    },
    {
        "book": "War and Peace",
        "author": "Leo Tolstoy",
        "publishing_year": "1869"
    },
    {
        "book": "Jane Eyre",
        "author": "Charlotte Brontë",
        "publishing_year": "1847"
    },
    {
        "book": "The Picture of Dorian Gray",
        "author": "Oscar Wilde",
        "publishing_year": "1890"
    },
    {
        "book": "Frankenstein",
        "author": "Mary Shelley",
        "publishing_year": "1818"
    }
] 